odoo/addons/l10n_es_aeat_mod296/README.rst
odoo/addons/l10n_es_aeat_mod296/__init__.py
odoo/addons/l10n_es_aeat_mod296/__manifest__.py
odoo/addons/l10n_es_aeat_mod296/data/aeat_export_mod296_data.xml
odoo/addons/l10n_es_aeat_mod296/data/aeat_export_mod296_line_data.xml
odoo/addons/l10n_es_aeat_mod296/data/tax_code_map_mod296_data.xml
odoo/addons/l10n_es_aeat_mod296/docs/DR296_2017.pdf
odoo/addons/l10n_es_aeat_mod296/docs/instrucciones_296.pdf
odoo/addons/l10n_es_aeat_mod296/docs/register_design_296_2008.pdf
odoo/addons/l10n_es_aeat_mod296/i18n/es.po
odoo/addons/l10n_es_aeat_mod296/i18n/l10n_es_aeat_mod296.pot
odoo/addons/l10n_es_aeat_mod296/migrations/13.0.1.1.0/noupdate_changes.xml
odoo/addons/l10n_es_aeat_mod296/migrations/13.0.1.1.0/post-migration.py
odoo/addons/l10n_es_aeat_mod296/models/__init__.py
odoo/addons/l10n_es_aeat_mod296/models/mod296.py
odoo/addons/l10n_es_aeat_mod296/readme/CONFIGURE.rst
odoo/addons/l10n_es_aeat_mod296/readme/CONTRIBUTORS.rst
odoo/addons/l10n_es_aeat_mod296/readme/DESCRIPTION.rst
odoo/addons/l10n_es_aeat_mod296/readme/USAGE.rst
odoo/addons/l10n_es_aeat_mod296/security/ir.model.access.csv
odoo/addons/l10n_es_aeat_mod296/security/ir_rule.xml
odoo/addons/l10n_es_aeat_mod296/static/description/icon.png
odoo/addons/l10n_es_aeat_mod296/static/description/icon_source.svg
odoo/addons/l10n_es_aeat_mod296/static/description/index.html
odoo/addons/l10n_es_aeat_mod296/tests/__init__.py
odoo/addons/l10n_es_aeat_mod296/tests/test_l10n_es_aeat_mod296.py
odoo/addons/l10n_es_aeat_mod296/views/mod296_views.xml
odoo13_addon_l10n_es_aeat_mod296-13.0.1.2.0.dist-info/METADATA
odoo13_addon_l10n_es_aeat_mod296-13.0.1.2.0.dist-info/WHEEL
odoo13_addon_l10n_es_aeat_mod296-13.0.1.2.0.dist-info/top_level.txt
odoo13_addon_l10n_es_aeat_mod296-13.0.1.2.0.dist-info/RECORD
